example_package_calculator/__init__.py
example_package_calculator/example.py
example_package_calculator-0.0.4.dist-info/METADATA
example_package_calculator-0.0.4.dist-info/WHEEL
example_package_calculator-0.0.4.dist-info/entry_points.txt
example_package_calculator-0.0.4.dist-info/license_files/LICENCE
example_package_calculator-0.0.4.dist-info/RECORD
