Metadata-Version: 2.1
Name: example-package-calculator
Version: 0.0.4
Summary: A simple calclualtor
Author-email: Andrius <osipovas.andrius@gmail.com>
Classifier: License :: OSI Approved :: MIT License
Classifier: Operating System :: OS Independent
Classifier: Programming Language :: Python :: 3
Requires-Python: >=3.7
